tracium/__init__.py
tracium/py.typed
tracium/api/__init__.py
tracium/api/endpoints.py
tracium/api/http_client.py
tracium/context/__init__.py
tracium/context/context_propagation.py
tracium/context/tenant_context.py
tracium/context/trace_context.py
tracium/core/__init__.py
tracium/core/client.py
tracium/core/config.py
tracium/core/version.py
tracium/helpers/__init__.py
tracium/helpers/call_hierarchy.py
tracium/helpers/global_state.py
tracium/helpers/logging_config.py
tracium/helpers/parallel_tracker.py
tracium/helpers/retry.py
tracium/helpers/retry_async.py
tracium/helpers/security.py
tracium/helpers/thread_helpers.py
tracium/helpers/validation.py
tracium/instrumentation/__init__.py
tracium/instrumentation/auto_detection.py
tracium/instrumentation/auto_instrumentation.py
tracium/instrumentation/auto_trace_tracker.py
tracium/instrumentation/decorators.py
tracium/integrations/__init__.py
tracium/integrations/anthropic.py
tracium/integrations/google.py
tracium/integrations/langchain.py
tracium/integrations/langgraph.py
tracium/integrations/openai.py
tracium/models/__init__.py
tracium/models/span_handle.py
tracium/models/trace_handle.py
tracium/models/trace_state.py
tracium/utils/__init__.py
tracium/utils/datetime_utils.py
tracium/utils/span_registry.py
tracium/utils/tags.py
tracium/utils/validation.py
tracium-0.1.0.dist-info/licenses/LICENSE
tracium-0.1.0.dist-info/METADATA
tracium-0.1.0.dist-info/WHEEL
tracium-0.1.0.dist-info/top_level.txt
tracium-0.1.0.dist-info/RECORD
