Metadata-Version: 2.4
Name: tracium
Version: 0.1.0
Summary: Official Python SDK for the Tracium telemetry and evaluation API. Automatic tracing for OpenAI, Anthropic, Google Gemini, LangChain, and LangGraph.
Author-email: Tracium <support@tracium.ai>
License-Expression: MIT
Project-URL: Homepage, https://tracium.ai
Project-URL: Repository, https://github.com/AntonijSimonovski/tracium-python
Project-URL: Documentation, https://docs.tracium.ai
Project-URL: Changelog, https://github.com/AntonijSimonovski/tracium-python/blob/main/CHANGELOG.md
Project-URL: Bug Tracker, https://github.com/AntonijSimonovski/tracium-python/issues
Keywords: tracium,telemetry,observability,llm,openai,anthropic,claude,gemini,langchain,monitoring,evaluation
Classifier: Development Status :: 4 - Beta
Classifier: Intended Audience :: Developers
Classifier: Programming Language :: Python :: 3
Classifier: Programming Language :: Python :: 3.10
Classifier: Programming Language :: Python :: 3.11
Classifier: Programming Language :: Python :: 3.12
Classifier: Programming Language :: Python :: 3.13
Classifier: Topic :: Software Development :: Libraries :: Python Modules
Classifier: Topic :: System :: Monitoring
Requires-Python: >=3.10
License-File: LICENSE
Requires-Dist: httpx<0.29,>=0.27
Requires-Dist: openai>=1.0.0
Requires-Dist: anthropic>=0.18.0
Requires-Dist: google-generativeai>=0.3.0
Requires-Dist: langchain>=0.1.0
Requires-Dist: langchain-core>=0.1.0
Requires-Dist: langgraph>=0.0.1
Requires-Dist: python-dotenv>=1.0.0
Requires-Dist: typing-extensions>=4.0
Provides-Extra: dev
Requires-Dist: pytest>=7.0; extra == "dev"
Requires-Dist: pytest-cov>=4.0; extra == "dev"
Requires-Dist: pytest-asyncio>=0.21.0; extra == "dev"
Requires-Dist: ruff>=0.1.0; extra == "dev"
Requires-Dist: mypy>=1.0; extra == "dev"
Requires-Dist: python-dotenv>=1.0.0; extra == "dev"
Provides-Extra: openai
Requires-Dist: openai>=1.0.0; extra == "openai"
Provides-Extra: anthropic
Requires-Dist: anthropic>=0.18.0; extra == "anthropic"
Provides-Extra: google
Requires-Dist: google-generativeai>=0.3.0; extra == "google"
Provides-Extra: langchain
Requires-Dist: langchain>=0.1.0; extra == "langchain"
Requires-Dist: langchain-core>=0.1.0; extra == "langchain"
Provides-Extra: langgraph
Requires-Dist: langgraph>=0.0.1; extra == "langgraph"
Provides-Extra: embeddings
Requires-Dist: sentence-transformers>=2.7.0; extra == "embeddings"
Provides-Extra: all
Requires-Dist: openai>=1.0.0; extra == "all"
Requires-Dist: anthropic>=0.18.0; extra == "all"
Requires-Dist: google-generativeai>=0.3.0; extra == "all"
Requires-Dist: langchain>=0.1.0; extra == "all"
Requires-Dist: langchain-core>=0.1.0; extra == "all"
Requires-Dist: langgraph>=0.0.1; extra == "all"
Requires-Dist: sentence-transformers>=2.7.0; extra == "all"
Dynamic: license-file
